{
    "symbols": [
        "ADA/USDT",
        "AXS/USDT",
        "BCH/USDT",
        "BNB/USDT",
        "CHZ/USDT",
        "DOGE/USDT",
        "DOT/USDT",
        "EOS/USDT",
        "ETC/USDT",
        "FIL/USDT",
        "LINK/USDT",
        "LTC/USDT",
        "LUNA/USDT",
        "MANA/USDT",
        "MATIC/USDT",
        "ONE/USDT",
        "RSR/USDT",
        "SOL/USDT",
        "XRP/USDT"
    ],
    
    "binanceApi": {
        "key": "U4dxVzVtWtlu778JK53LwEjFBImpoO8XLiXalWlzeszEPptzLAj557lx3wRm3YRc",
        "secret": "1MwOpUJqY6HyIrkXHQbixZJQcOF9EIHAhsJllTzFJOI1dGMRTWkk2z9Jo7Ly27CJ"
    },

    "telegramToken": "1809950671:AAExYTyxWpaYu5-bZ87wFKog_Ru9wYwRWCM",

    "useCatchBot": true,
    "useBucketBot": false,

    "bucket":
        {"targetDI": 0.021, "marginRatio": 0.5, "profitPercent": 0.01, "stoplossTriggerPercent": 0.003}
    ,
    "catch": [
        {"targetDI": 0.033, "marginRatio": 3, "profitPercent": 0.019, "stoplossTriggerPercent": 0.007},
        {"targetDI": 0.033, "marginRatio": 5, "profitPercent": 0.015, "stoplossTriggerPercent": 0.005},
        {"targetDI": 0.045, "marginRatio": 10, "profitPercent": 0.03, "stoplossTriggerPercent": 0.005}
    ],
    "panicSellAlarm": {
        "use": true,
        "deltaPercent": -0.5
    },
    "log": {
        "fileLevel": "DEBUG", 
        "consoleLevel": "INFO"
    }
}